{
  "meta": {
    "id": "kanz-ar",
    "lang": "ar",
    "dir": "rtl",
    "fonts": [
      "Amiri",
      "Tajawal"
    ],
    "audio": true,
    "audioPath": "audios/{id}.opus",
    "numerals": "arabic",
    "buildMinWords": 4,
    "blankMinWords": 3,
    "stopWords": [
      "من",
      "في",
      "على",
      "إلى",
      "عن",
      "مع",
      "هو",
      "هي",
      "هم",
      "أن",
      "إن",
      "كان",
      "كانت",
      "وهو",
      "وهي",
      "التي",
      "الذي",
      "ما",
      "لا",
      "أو",
      "و",
      "ال"
    ]
  },
  "ui": {
    "appTitle": "منتقى كنز الأطفال",
    "searchPlaceholder": "ابحث...",
    "allSections": "جميع الأسئلة",
    "allSectionsShort": "الكل",
    "allChapters": "جميع الأبواب",
    "weakSpots": "نقاط الضعف",
    "weakSpotsLabel": "نقاط الضعف ({n} سؤال) ⚠",
    "questionCount": "عدد الأسئلة:",
    "quizType": "نوع الاختبار:",
    "startQuiz": "ابدأ الاختبار",
    "next": "التالي",
    "retry": "إعادة",
    "score": "النقاط",
    "questionNum": "س {n}",
    "answerLabel": "الجواب",
    "showAnswer": "إظهار الجواب",
    "close": "إغلاق",
    "listen": "استمع",
    "replay": "إعادة ↺",
    "audioError": "تعذّر التشغيل",
    "save": "حفظ",
    "saved": "تمت الإضافة إلى المحفوظات",
    "unsaved": "تمت الإزالة من المحفوظات",
    "favoritesTitle": "المحفوظات",
    "noFavsTitle": "لا توجد محفوظات بعد!",
    "noFavsHint": "اضغط على أي سؤال لحفظه",
    "noResults": "لا نتائج",
    "browseNav": "تصفح",
    "favsNav": "محفوظات",
    "quizNav": "اختبار",
    "counterSuffix": "سؤال",
    "placeTilesHint": "اضغط على الكلمات لترتيبها...",
    "checkAnswer": "تحقق",
    "correctFeedback": "أحسنت! ترتيب صحيح",
    "wrongOrderFeedback": "الترتيب الصحيح:",
    "correctBlankFeedback": "أحسنت! الكلمة صحيحة",
    "wrongBlankFeedback": "الكلمة الصحيحة:",
    "correctListenFeedback": "أحسنت! الجواب الصحيح",
    "wrongListenFeedback": "الجواب الصحيح:",
    "correctMCQFeedback": "أحسنت! إجابة صحيحة",
    "wrongMCQFeedback": "الإجابة الصحيحة:",
    "notEnoughQuestions": "لا توجد أسئلة كافية لهذا النوع في هذا الباب",
    "resultPerfect": "مثالي!",
    "resultPerfectMsg": "١٠٠٪ صحيح! أنت نجم!",
    "resultGreat": "ممتاز!",
    "resultGreatMsg": "أداء رائع جداً! استمر هكذا.",
    "resultGood": "جيد!",
    "resultGoodMsg": "تقدم جيد، واصل المذاكرة.",
    "resultTryAgain": "حاول مجدداً!",
    "resultTryAgainMsg": "لا بأس، المثابرة طريق النجاح.",
    "modeMCQ": "اختيار",
    "modeBuild": "ترتيب",
    "modeBlank": "تكميل",
    "modeListen": "استماع",
    "scopeAll": "الكل",
    "scopeQ": "س",
    "scopeA": "ج",
    "aboutBtn": "عن التطبيق",
    "share": "مشاركة",
    "shareImage": "مشاركة كصورة",
    "copyText": "نسخ النص",
    "copied": "تم النسخ!",
    "deepLinkCopied": "تم نسخ الرابط!",
    "shareAppUrl": "مشاركة رابط التطبيق",
    "fontSizeLabel": "حجم الخط",
    "contrastLabel": "وضع التباين",
    "settingsTitle": "الإعدادات"
  },
  "items": [
    {
      "id": 1,
      "q": "ما هي مراتب الدين ؟",
      "a": "ثلاث: 1-  الإسلام.    2- والإيمان.   3- والإحسان .",
      "section": "باب الإيمان، ومراتب الدين"
    },
    {
      "id": 2,
      "q": "من ربك ؟",
      "a": "ربي الله.",
      "section": "باب الإيمان، ومراتب الدين"
    },
    {
      "id": 3,
      "q": "من نبيك؟",
      "a": "نبيي محمد - صلى الله عليه وسلم.",
      "section": "باب الإيمان، ومراتب الدين"
    },
    {
      "id": 4,
      "q": "ما دينك؟",
      "a": "ديني الإسلام.",
      "section": "باب الإيمان، ومراتب الدين"
    },
    {
      "id": 5,
      "q": "من خلقك؟",
      "a": "الله خلقني وخلق جميع ال‍مخلوقات.",
      "section": "باب الإيمان، ومراتب الدين"
    },
    {
      "id": 6,
      "q": "ل‍م‍اذا خلقنا الله؟",
      "a": "خلقنا لعبادته.",
      "section": "باب الإيمان، ومراتب الدين"
    },
    {
      "id": 7,
      "q": "كم أركان الإسلام؟",
      "a": "خمسة، وهي: * شهادة أن لا إله إلا الله، وأن م‍حمدا رسول الله. * وإقام الصلاة. * وإيتاء الزكاة. * وصوم رمضان. * وحج البيت ل‍من استطاع إليه سبيلا.",
      "section": "باب الإيمان، ومراتب الدين"
    },
    {
      "id": 8,
      "q": "ما هو الدين الذي لا يقبل الله غيره؟",
      "a": "هو: الإسلام.",
      "section": "باب الإيمان، ومراتب الدين"
    },
    {
      "id": 9,
      "q": "من هم شر البرية، ومن هم خير البرية؟",
      "a": "شر البرية الكفار، وخير البرية ال‍مؤمنون.",
      "section": "باب الإيمان، ومراتب الدين"
    },
    {
      "id": 10,
      "q": "من هم أهل الكتاب؟",
      "a": "هم اليهود، والنصارى.",
      "section": "باب الإيمان، ومراتب الدين"
    },
    {
      "id": 11,
      "q": "هل دين الإسلام كامل أم يحتاج إلى تكميل؟",
      "a": "دين الإسلام كامل.",
      "section": "باب الإيمان، ومراتب الدين"
    },
    {
      "id": 12,
      "q": "من أين يأخذ ال‍مسلم دينه؟",
      "a": "من الكتاب والسنة.",
      "section": "باب الإيمان، ومراتب الدين"
    },
    {
      "id": 13,
      "q": "ما عقيدتك؟",
      "a": "سني سلفي.",
      "section": "باب الإيمان، ومراتب الدين"
    },
    {
      "id": 14,
      "q": "كم أركان الإيم‍ان؟",
      "a": "ستة: * الإيم‍ان بالله. * وملائكته. * وكتبه. *ورسله. * واليوم الآخر. * والقدر خيره وشره.",
      "section": "باب الإيمان، ومراتب الدين"
    },
    {
      "id": 15,
      "q": "ما هو أول واجب على العبيد؟",
      "a": "توحيد الله تعالى.",
      "section": "باب الإيمان، ومراتب الدين"
    },
    {
      "id": 16,
      "q": "ما هو حق الله على العباد؟",
      "a": "أن يعبدوه، ولا يشركوا به شيئا.",
      "section": "باب الإيمان، ومراتب الدين"
    },
    {
      "id": 17,
      "q": "ما هو حق العباد على الله؟",
      "a": "أن لا يعذب من لا يشرك به شيئا.",
      "section": "باب الإيمان، ومراتب الدين"
    },
    {
      "id": 18,
      "q": "كم أقسام توحيد الله؟",
      "a": "ثلاثة أقسام هي: توحيد الألوهية. توحيد الربوبية. توحيد الأسماء والصفات.",
      "section": "باب الإيمان، ومراتب الدين"
    },
    {
      "id": 19,
      "q": "ما هي كلمة التوحيد؟",
      "a": "لا إله إلا الله.",
      "section": "باب الإيمان، ومراتب الدين"
    },
    {
      "id": 20,
      "q": "ما معنى لا إله إلا الله؟",
      "a": "لا معبود حق إلا الله.",
      "section": "باب الإيمان، ومراتب الدين"
    },
    {
      "id": 21,
      "q": "أين الله، وما الدليل؟",
      "a": "في السماء، والدليل قوله تعالى: (الرحمن على العرش استوى) [سورة طه:5].",
      "section": "باب الإيمان، ومراتب الدين"
    },
    {
      "id": 22,
      "q": "هل الله معنا؟",
      "a": "معنا: بعلمه، وإحاطته، وسمعه، ورؤيته.",
      "section": "باب الإيمان، ومراتب الدين"
    },
    {
      "id": 23,
      "q": "هل أحد يعلم الغيب غير الله؟",
      "a": "لا يعلم الغيب إلا الله.",
      "section": "باب الإيمان، ومراتب الدين"
    },
    {
      "id": 24,
      "q": "ما أعظم حسنة؟",
      "a": "توحيد الله تعالى.",
      "section": "باب الإيمان، ومراتب الدين"
    },
    {
      "id": 25,
      "q": "ما أعظم سيئة؟",
      "a": "الشرك بالله تعالى.",
      "section": "باب الإيمان، ومراتب الدين"
    },
    {
      "id": 26,
      "q": "ما حكم ترك الصلاة؟",
      "a": "كفر.",
      "section": "باب الإيمان، ومراتب الدين"
    },
    {
      "id": 27,
      "q": "ما حكم سب الصحابة أو لعنهم؟",
      "a": "كفر.",
      "section": "باب الإيمان، ومراتب الدين"
    },
    {
      "id": 28,
      "q": "من هم الذين يسبون الصحابة؟",
      "a": "الرافضة.",
      "section": "باب الإيمان، ومراتب الدين"
    },
    {
      "id": 29,
      "q": "مم خلقت ال‍ملائكة؟",
      "a": "من نور.",
      "section": "الإيمان بالملائكة"
    },
    {
      "id": 30,
      "q": "من هو أفضل ال‍ملائكة؟",
      "a": "جبريل ’.",
      "section": "الإيمان بالملائكة"
    },
    {
      "id": 31,
      "q": "من هو الذي نزل بالوحي على الأنبياء من الله؟",
      "a": "جبريل عليه السلام.",
      "section": "الإيمان بالملائكة"
    },
    {
      "id": 32,
      "q": "هل للملائكة أجنحة؟",
      "a": "نعم.",
      "section": "الإيمان بالملائكة"
    },
    {
      "id": 33,
      "q": "كم جناحا ل‍جبريل عليه السلام؟",
      "a": "ستم‍ائة جناح.",
      "section": "الإيمان بالملائكة"
    },
    {
      "id": 34,
      "q": "ل‍من تضع ال‍ملائكة أجنحتها؟",
      "a": "لطالب العلم.",
      "section": "الإيمان بالملائكة"
    },
    {
      "id": 35,
      "q": "هل نرى ال‍جن والشياطين على هيئتهم؟",
      "a": "لا.",
      "section": "الإيمان بالملائكة"
    },
    {
      "id": 36,
      "q": "هل نخاف من ال‍جن والشياطين؟",
      "a": "لا، إنم‍ا نخاف من الله وحده.",
      "section": "الإيمان بالملائكة"
    },
    {
      "id": 37,
      "q": "ما مصير مؤمن ال‍جن وكافرهم؟",
      "a": "مؤمنهم يدخل ال‍جنة، وكافرهم يدخل النار.",
      "section": "الإيمان بالملائكة"
    },
    {
      "id": 38,
      "q": "هل الشيطان عدو لنا؟",
      "a": "نعم.",
      "section": "الإيمان بالملائكة"
    },
    {
      "id": 39,
      "q": "هل ال‍جن يعلمون الغيب؟",
      "a": "لا.",
      "section": "الإيمان بالملائكة"
    },
    {
      "id": 40,
      "q": "اذكر أربعة من الكتب ال‍منزلة؟",
      "a": "القرآن، والتوراة، والإنجيل، والزبور.",
      "section": "الإيمان بالكتب"
    },
    {
      "id": 41,
      "q": "اذكر على من نزل كل كتاب منها؟",
      "a": "القرآن على م‍حمد، والتوراة على موسى، والإنجيل على عيسى، والزبور على داود صلى الله عليهم وسلم أجمعين.",
      "section": "الإيمان بالكتب"
    },
    {
      "id": 42,
      "q": "ما هو أفضل هذه الكتب؟",
      "a": "القرآن.",
      "section": "الإيمان بالكتب"
    },
    {
      "id": 43,
      "q": "هل القرآن عربي أم أعجمي؟",
      "a": "القرآن عربي.",
      "section": "الإيمان بالكتب"
    },
    {
      "id": 44,
      "q": "من هو أبو البشر؟",
      "a": "آدم عليه السلام.",
      "section": "الإيمان بالرسل"
    },
    {
      "id": 45,
      "q": "من هو أول الأنبياء؟",
      "a": "آدم عليه السلام.",
      "section": "الإيمان بالرسل"
    },
    {
      "id": 46,
      "q": "من هو آخر الأنبياء؟",
      "a": "م‍حمد - صلى الله عليه وسلم.",
      "section": "الإيمان بالرسل"
    },
    {
      "id": 47,
      "q": "من هو أفضل الرسل؟",
      "a": "م‍حمد - صلى الله عليه وسلم.",
      "section": "الإيمان بالرسل"
    },
    {
      "id": 48,
      "q": "هل الأنبياء رعوا الغنم؟",
      "a": "نعم، وكان النبي صلى الله عليه وسلم يرعاها على قراريط لأهل مكة.",
      "section": "الإيمان بالرسل"
    },
    {
      "id": 49,
      "q": "من أول الرسل إلى أهل الأرض؟",
      "a": "نوح عليه السلام.",
      "section": "الإيمان بالرسل"
    },
    {
      "id": 50,
      "q": "كم لبث نوح في قومه؟",
      "a": "ألف سنة إلا خمسين عاما.",
      "section": "الإيمان بالرسل"
    },
    {
      "id": 51,
      "q": "كيف نجى الله نوحا ومن اتبعه؟",
      "a": "في السفينة.",
      "section": "الإيمان بالرسل"
    },
    {
      "id": 52,
      "q": "بم‍اذا أهلك الله قوم نوح؟",
      "a": "بالطوفان.",
      "section": "الإيمان بالرسل"
    },
    {
      "id": 53,
      "q": "من هو أبو الأنبياء؟",
      "a": "إبراهيم عليه السلام.",
      "section": "الإيمان بالرسل"
    },
    {
      "id": 54,
      "q": "من هي أم إسماعيل ‘؟",
      "a": "هاجر عليها السلام.",
      "section": "الإيمان بالرسل"
    },
    {
      "id": 55,
      "q": "ما هي البئر التي نبعت لأم إسماعيل؟",
      "a": "زمزم.",
      "section": "الإيمان بالرسل"
    },
    {
      "id": 56,
      "q": "أي أولاد إبراهيم الذي أمر الله بذبحه؟",
      "a": "هو إسماعيل عليه السلام.",
      "section": "الإيمان بالرسل"
    },
    {
      "id": 57,
      "q": "بم‍اذا فدى الله إسماعيل؟",
      "a": "فداه بذبح عظيم وهو الكبش.",
      "section": "الإيمان بالرسل"
    },
    {
      "id": 58,
      "q": "من الذي قال أنا ربكم الأعلى؟ وكيف أهلكه الله؟",
      "a": "فرعون لعنه الله، وأهلكه الله بالغرق.",
      "section": "الإيمان بالرسل"
    },
    {
      "id": 59,
      "q": "من هو وزير فرعون؟",
      "a": "هامان لعنه الله.",
      "section": "الإيمان بالرسل"
    },
    {
      "id": 60,
      "q": "من هو الرسول إلى قوم ثمود؟",
      "a": "صالح عليه السلام.",
      "section": "الإيمان بالرسل"
    },
    {
      "id": 61,
      "q": "ما هي الآية التي أرسلها الله إلى قوم ثمود؟",
      "a": "الناقة.",
      "section": "الإيمان بالرسل"
    },
    {
      "id": 62,
      "q": "بم‍اذا أهلك الله قوم ثمود؟",
      "a": "بالصيحة.",
      "section": "الإيمان بالرسل"
    },
    {
      "id": 63,
      "q": "من هو الرسول الذي أرسله الله لقوم عاد؟",
      "a": "هود عليه السلام.",
      "section": "الإيمان بالرسل"
    },
    {
      "id": 64,
      "q": "أين سكن قوم هود؟",
      "a": "في الأحقاف باليمن.",
      "section": "الإيمان بالرسل"
    },
    {
      "id": 65,
      "q": "بم‍اذا أهلك الله قوم عاد؟",
      "a": "بالريح الباردة الشديدة.",
      "section": "الإيمان بالرسل"
    },
    {
      "id": 66,
      "q": "من هو النبي الذي سخر الله له ال‍جن والإنس والطير والريح؟",
      "a": "سليم‍ان عليه السلام.",
      "section": "الإيمان بالرسل"
    },
    {
      "id": 67,
      "q": "من هو النبي الذي كلم ال‍هدهد وسمع كلام النملة؟",
      "a": "سليم‍ان عليه السلام.",
      "section": "الإيمان بالرسل"
    },
    {
      "id": 68,
      "q": "من هو النبي الذي ابتـلي بال‍مرض فصبر وشكر؟",
      "a": "نبي الله أيوب عليه السلام.",
      "section": "الإيمان بالرسل"
    },
    {
      "id": 69,
      "q": "من هو النبي الذي كان يعمل نجارا؟",
      "a": "زكريا عليه السلام.",
      "section": "الإيمان بالرسل"
    },
    {
      "id": 70,
      "q": "من هو النبي الذي بعث إلى أهل مدين؟",
      "a": "شعيب عليه السلام.",
      "section": "الإيمان بالرسل"
    },
    {
      "id": 71,
      "q": "من هو النبي الذي رفعه الله إليه ولا يزال حيا؟",
      "a": "عيسى عليه السلام.",
      "section": "الإيمان بالرسل"
    },
    {
      "id": 72,
      "q": "هل في القبر نعيم وعذاب؟",
      "a": "نعم، في القبر نعيم وعذاب ل‍من كان له أهل.",
      "section": "الإيمان باليوم الآخر"
    },
    {
      "id": 73,
      "q": "ما هي ال‍مسائل التي يسأل عنها العبد في القبر؟",
      "a": "من ربك؟ وما دينك؟ ومن نبيك؟.",
      "section": "الإيمان باليوم الآخر"
    },
    {
      "id": 74,
      "q": "بم‍اذا يجيب ال‍مسلم؟",
      "a": "يقول ربي الله، وديني الإسلام، ونبيي م‍حمد - صلى الله عليه وسلم.",
      "section": "الإيمان باليوم الآخر"
    },
    {
      "id": 75,
      "q": "بم‍اذا يجيب الكافر وال‍منافق؟",
      "a": "ها، ها، لا أدري.",
      "section": "الإيمان باليوم الآخر"
    },
    {
      "id": 76,
      "q": "في أي يوم تقوم الساعة؟",
      "a": "في يوم ال‍جمعة.",
      "section": "الإيمان باليوم الآخر"
    },
    {
      "id": 77,
      "q": "هل إبليس حي الآن، أم قد مات؟",
      "a": "هو حي إلى اليوم ال‍معلوم الذي أذن الله بهلاكه فيه.",
      "section": "الإيمان باليوم الآخر"
    },
    {
      "id": 78,
      "q": "من هو أول من تنشق عنه الأرض؟",
      "a": "هو النبي - صلى الله عليه وسلم.",
      "section": "الإيمان باليوم الآخر"
    },
    {
      "id": 79,
      "q": "كيف يحشر الناس؟",
      "a": "حفاة عراة غرلا.",
      "section": "الإيمان باليوم الآخر"
    },
    {
      "id": 80,
      "q": "ما معنى غرلا؟",
      "a": "غير م‍ختونين",
      "section": "الإيمان باليوم الآخر"
    },
    {
      "id": 81,
      "q": "ماذا يتمنى الكافر يوم القيامة؟",
      "a": "أن يكون ترابا.",
      "section": "الإيمان باليوم الآخر"
    },
    {
      "id": 82,
      "q": "بم‍اذا توزن الأعمال يوم القيامة؟",
      "a": "بال‍ميزان.",
      "section": "الإيمان باليوم الآخر"
    },
    {
      "id": 83,
      "q": "ما هو الصراط؟",
      "a": "هو جسر يضرب على جهنم.",
      "section": "الإيمان باليوم الآخر"
    },
    {
      "id": 84,
      "q": "ما جزاء ال‍مؤمنين، وما جزاء الكافرين يوم القيامة؟",
      "a": "جزاء ال‍مؤمنين ال‍جنة، وجزاء الكافرين النار.",
      "section": "الإيمان باليوم الآخر"
    },
    {
      "id": 85,
      "q": "هل ال‍جنة والنار موجودتان الآن؟",
      "a": "نعم.",
      "section": "الإيمان باليوم الآخر"
    },
    {
      "id": 86,
      "q": "أين ال‍جنة؟ وأين النار؟",
      "a": "ال‍جنة في أعلى عليين في السماء، والنار في أسفل سافلين في الأرض السفلى.",
      "section": "الإيمان باليوم الآخر"
    },
    {
      "id": 87,
      "q": "كم أبواب ال‍جنة وأبواب النار؟",
      "a": "أبواب ال‍جنة ثمانية، وأبواب النار سبعة.",
      "section": "الإيمان باليوم الآخر"
    },
    {
      "id": 88,
      "q": "هل في ال‍جنة موت؟",
      "a": "لا، ليس في ال‍جنة موت.",
      "section": "الإيمان باليوم الآخر"
    },
    {
      "id": 89,
      "q": "من هو الذي يستفتح باب ال‍جنة، وأول من يدخلها؟",
      "a": "النبي - صلى الله عليه وسلم.",
      "section": "الإيمان باليوم الآخر"
    },
    {
      "id": 90,
      "q": "هل يرى ال‍مؤمنون رب‍هم يوم القيامة؟",
      "a": "نعم، في عرصات القيامة، وفي ال‍جنة.",
      "section": "الإيمان باليوم الآخر"
    },
    {
      "id": 91,
      "q": "متى ولد النبي - صلى الله عليه وسلم؟",
      "a": "عام الفيل.",
      "section": "الإيمان باليوم الآخر"
    },
    {
      "id": 92,
      "q": "أين ولد النبي - صلى الله عليه وسلم؟",
      "a": "في مكة.",
      "section": "الإيمان باليوم الآخر"
    },
    {
      "id": 93,
      "q": "ل‍م‍اذا سمي عام الفيل؟",
      "a": "لأن أبرهة ال‍حبشي حاول هدم الكعبة بجيش معه فيل في ذلك العام.",
      "section": "الإيمان باليوم الآخر"
    },
    {
      "id": 94,
      "q": "هل استطاع هدم الكعبة؟",
      "a": "لا، بل أهلكه الله بالطير، ترميهم بحجارة من نار.",
      "section": "الإيمان باليوم الآخر"
    },
    {
      "id": 95,
      "q": "من هو أبو النبي - صلى الله عليه وسلم؟",
      "a": "هو عبد الله بن عبد ال‍مطلب بن هاشم.",
      "section": "الإيمان باليوم الآخر"
    },
    {
      "id": 96,
      "q": "من هو جد النبي - صلى الله عليه وسلم؟",
      "a": "عبد ال‍مطلب بن هاشم بن عبد مناف.",
      "section": "الإيمان باليوم الآخر"
    },
    {
      "id": 97,
      "q": "من أي قبيلة يكون - صلى الله عليه وسلم؟",
      "a": "من قريش.",
      "section": "الإيمان باليوم الآخر"
    },
    {
      "id": 98,
      "q": "من هي أمه - صلى الله عليه وسلم؟",
      "a": "هي آمنة بنت وهب.",
      "section": "الإيمان باليوم الآخر"
    },
    {
      "id": 99,
      "q": "اذكر بعض مرضعاته - صلى الله عليه وسلم؟",
      "a": "حليمة السعدية، وثويبة مولاة أبي ل‍هب.",
      "section": "الإيمان باليوم الآخر"
    },
    {
      "id": 100,
      "q": "من الذي كفل النبي - صلى الله عليه وسلم؟",
      "a": "جده عبد ال‍مطلب، ثم بعده عمه أبو طالب.",
      "section": "الإيمان باليوم الآخر"
    },
    {
      "id": 101,
      "q": "من هي أول زوجاته - صلى الله عليه وسلم؟",
      "a": "خدي‍جة بنت خويلد.",
      "section": "الإيمان باليوم الآخر"
    },
    {
      "id": 102,
      "q": "ماذا كان كفار قريش يدعون النبي - صلى الله عليه وسلم قبل البعثة؟",
      "a": "الصادق الأمين.",
      "section": "الإيمان باليوم الآخر"
    },
    {
      "id": 103,
      "q": "اذكر أولاد النبي - صلى الله عليه وسلم؟",
      "a": "إبراهيم، وفاطمة، وأم كلثوم، ورقية، وزينب، والقاسم، وعبد الله.",
      "section": "الإيمان باليوم الآخر"
    },
    {
      "id": 104,
      "q": "من أي زوجات الرسول - صلى الله عليه وسلم كان أولاده؟",
      "a": "كلهم من خدي‍جة رضي الله عنها، إلا إبراهيم، فمن مارية القبطية (سريته).",
      "section": "الإيمان باليوم الآخر"
    },
    {
      "id": 105,
      "q": "أين كان النبي - صلى الله عليه وسلم يتعبد في بدء أمره؟",
      "a": "في غار حراء.",
      "section": "الإيمان باليوم الآخر"
    },
    {
      "id": 106,
      "q": "متى نزل عليه الوحي - صلى الله عليه وسلم؟",
      "a": "حين بلغ الأربعين سنة.",
      "section": "الإيمان باليوم الآخر"
    },
    {
      "id": 107,
      "q": "من أين هاجر النبي - صلى الله عليه وسلم وإلى أين؟",
      "a": "من مكة إلى ال‍مدينة.",
      "section": "الإيمان باليوم الآخر"
    },
    {
      "id": 108,
      "q": "كم لبث النبي - صلى الله عليه وسلم في مكة بعد البعثة؟",
      "a": "ثلاث عشرة سنة.",
      "section": "الإيمان باليوم الآخر"
    },
    {
      "id": 109,
      "q": "من هو أول من أسلم مع النبي - صلى الله عليه وسلم؟",
      "a": "أول من أسلم: من الرجال: أبو بكر الصديق. ومن الصبيان: علي بن أبى طالب. ومن النساء: خدي‍جة بنت خويلد رضي الله عنهم أجمعين.",
      "section": "الإيمان باليوم الآخر"
    },
    {
      "id": 110,
      "q": "إلى أين أسري بالنبي - صلى الله عليه وسلم؟",
      "a": "إلى بيت ال‍مقدس.",
      "section": "الإيمان باليوم الآخر"
    },
    {
      "id": 111,
      "q": "إلى أين عرج به - صلى الله عليه وسلم؟",
      "a": "إلى السماء.",
      "section": "الإيمان باليوم الآخر"
    },
    {
      "id": 112,
      "q": "ما هي الدابة التي أسري به عليها - صلى الله عليه وسلم؟",
      "a": "البراق.",
      "section": "الإيمان باليوم الآخر"
    },
    {
      "id": 113,
      "q": "من هو صاحب رسول الله - صلى الله عليه وسلم في ال‍هجرة؟",
      "a": "أبو بكر رضي الله عنه.",
      "section": "الصحابة رضي الله عنهم"
    },
    {
      "id": 114,
      "q": "من هي ذات النطاقين؟",
      "a": "هي أسماء بنت أبى بكر رضي الله عنها.",
      "section": "الصحابة رضي الله عنهم"
    },
    {
      "id": 115,
      "q": "ما اسم الغار الذي اختبأ فيه - صلى الله عليه وسلم وصاحبه في ال‍هجرة؟",
      "a": "غار ثور.",
      "section": "الصحابة رضي الله عنهم"
    },
    {
      "id": 116,
      "q": "من هو أفضل الصحابة؟",
      "a": "هو أبو بكر رضي الله عنه.",
      "section": "الصحابة رضي الله عنهم"
    },
    {
      "id": 117,
      "q": "من هم ال‍خلفاء الراشدون؟",
      "a": "أبو بكر الصديق، ثم عمر بن ال‍خطاب، ثم عثم‍ان بن عفان، ثم علي بن أبي طالب رضي الله عنهم.",
      "section": "الصحابة رضي الله عنهم"
    },
    {
      "id": 118,
      "q": "من سيدا شباب أهل ال‍جنة؟",
      "a": "ال‍حسن وال‍حسين رضي الله عنه.",
      "section": "الصحابة رضي الله عنهم"
    },
    {
      "id": 119,
      "q": "من هو أسد الله وأسد رسوله؟",
      "a": "حمزة بن عبد ال‍مطلب رضي الله عنه.",
      "section": "الصحابة رضي الله عنهم"
    },
    {
      "id": 120,
      "q": "من هو ترجمان القران، وحبر الأمة؟",
      "a": "عبد الله بن عباس رضي الله عنهما.",
      "section": "الصحابة رضي الله عنهم"
    },
    {
      "id": 121,
      "q": "من هو أكثر من روى الأحاديث من الصحابة؟",
      "a": "أبو هريرة رضي الله عنه.",
      "section": "الصحابة رضي الله عنهم"
    },
    {
      "id": 122,
      "q": "من هي سيدة نساء ال‍جنة؟",
      "a": "فاطمة رضي الله عنها بنت رسول الله - صلى الله عليه وسلم.",
      "section": "الصحابة رضي الله عنهم"
    },
    {
      "id": 123,
      "q": "من هي أعلم النساء؟",
      "a": "عائشة رضي الله عنها.",
      "section": "الصحابة رضي الله عنهم"
    },
    {
      "id": 124,
      "q": "من هي أول النساء إسلاما؟",
      "a": "خدي‍جة بنت خويلد رضي الله عنها.",
      "section": "الصحابة رضي الله عنهم"
    },
    {
      "id": 125,
      "q": "ما هي أعظم معارك ال‍مسلمين؟",
      "a": "غزوة بدر الكبرى.",
      "section": "الصحابة رضي الله عنهم"
    },
    {
      "id": 126,
      "q": "ماذا فعل ال‍مسلمون حين علموا بخروج الأحزاب ل‍حرب‍هم؟",
      "a": "حفروا ال‍خندق.",
      "section": "الصحابة رضي الله عنهم"
    },
    {
      "id": 127,
      "q": "هل القرآن م‍خلوق؟",
      "a": "لا، بل هو كلام الله، منزل، غير م‍خلوق.",
      "section": "القرآن الكريم"
    },
    {
      "id": 128,
      "q": "في أي ليلة نزل القرآن؟",
      "a": "في ليلة القدر في شهر رمضان.",
      "section": "القرآن الكريم"
    },
    {
      "id": 129,
      "q": "ما هو أول ما نزل من القرآن؟",
      "a": "ال‍خمس الآيات الأولى من سورة العلق.",
      "section": "القرآن الكريم"
    },
    {
      "id": 130,
      "q": "هل القرآن عربي أم أعجمي؟",
      "a": "القرآن عربي.",
      "section": "القرآن الكريم"
    },
    {
      "id": 131,
      "q": "كم عدد سور القرآن؟",
      "a": "114 سورة.",
      "section": "القرآن الكريم"
    },
    {
      "id": 132,
      "q": "ما أطول سورة في القرآن؟",
      "a": "سورة البقرة.",
      "section": "القرآن الكريم"
    },
    {
      "id": 133,
      "q": "ما أقصر سورة من القرآن؟",
      "a": "سورة الكوثر.",
      "section": "القرآن الكريم"
    },
    {
      "id": 134,
      "q": "ما أعظم سورة من القرآن؟",
      "a": "سورة الفات‍حة.",
      "section": "القرآن الكريم"
    },
    {
      "id": 135,
      "q": "ما أعظم آية من القرآن؟",
      "a": "آية الكرسي.",
      "section": "القرآن الكريم"
    },
    {
      "id": 136,
      "q": "ما هي أم القرآن؟",
      "a": "هي سورة الفات‍حة.",
      "section": "القرآن الكريم"
    },
    {
      "id": 137,
      "q": "ما هي الآية التي إذا قرأها ال‍مسلم قبل نومه لا يقربه شيطان؟",
      "a": "آية الكرسي.",
      "section": "القرآن الكريم"
    },
    {
      "id": 138,
      "q": "ما هي الآيات التي من حفظها عصم من الدجال؟",
      "a": "العشر الآيات الأولى من سورة الكهف.",
      "section": "القرآن الكريم"
    },
    {
      "id": 139,
      "q": "ما هي السورة التي تعدل ثلث القرآن؟",
      "a": "قل هو الله أحد.",
      "section": "القرآن الكريم"
    },
    {
      "id": 140,
      "q": "ما هي ال‍معوذتان؟",
      "a": "قل أعوذ برب الفلق، وقل أعوذ برب الناس.",
      "section": "القرآن الكريم"
    },
    {
      "id": 141,
      "q": "ما هي السورة التي قرأها أبوسعيد ال‍خدري على ال‍ملدوغ وكانت رقية؟",
      "a": "الفات‍حة.",
      "section": "القرآن الكريم"
    },
    {
      "id": 142,
      "q": "ما حكم ماء البحر؟",
      "a": "البحر: هو الطهور ماؤه، ال‍حل ميتته.",
      "section": "الطهارة"
    },
    {
      "id": 143,
      "q": "متى يصبح ال‍م‍اء نجسا؟",
      "a": "إذا تغير لونه، أو ري‍حه، أو طعمه؛ بنجاسة ت‍حدث فيه.",
      "section": "الطهارة"
    },
    {
      "id": 144,
      "q": "الاستجم‍ار بكم يكون من الأحجار؟",
      "a": "إذا استجمر فليوتر، ولا يكون أقل من ثلاث. يعني: بثلاث أو خمس أو سبع وهكذا.",
      "section": "الطهارة"
    },
    {
      "id": 145,
      "q": "إذا ولغ الكلب في الإناء فم‍ا ال‍حكم؟",
      "a": "يغسل سبع مرات، أولاهن بالتراب.",
      "section": "الطهارة"
    },
    {
      "id": 146,
      "q": "هل ال‍هرة نجسة؟",
      "a": "لا؛ إنم‍ا هي من الطوافين عليكم.",
      "section": "الطهارة"
    },
    {
      "id": 147,
      "q": "ماذا نفعل إذا وقع الذباب في الشراب؟",
      "a": "نغمسه، ثم ننزعه؛ فإن في أحد جناحيه داء، وفي الآخر شفاء.",
      "section": "الطهارة"
    },
    {
      "id": 148,
      "q": "ما حكم الصلاة بغير وضوء؟",
      "a": "صلاة باطلة.",
      "section": "الطهارة"
    },
    {
      "id": 149,
      "q": "اذكر كيفية الوضوء باختصار؟",
      "a": "يسمي الله، ثم يغسل كفيه إلى الرسغين ثلاث مرات، ثم يتمضمض ويستنشق ويستنثر ثلاثا، ثم يغسل وجهه ثلاثا، ثم يغسل يديه إلى ال‍مرفقين ثلاثا، ثم يمسح رأسه مرة واحدة، ثم يغسل رجليه إلى الكعبين ثلاثا.",
      "section": "الطهارة"
    },
    {
      "id": 150,
      "q": "كيف يعرف النبي - صلى الله عليه وسلم أمته يوم القيامة؟",
      "a": "يأتونه غرا م‍حجلين من آثار الوضوء.",
      "section": "الطهارة"
    },
    {
      "id": 151,
      "q": "ما هي نواقض الوضوء؟",
      "a": "ال‍خارج من القبل والدبر، والنوم ال‍مستغرق، وأكل ل‍حم الإبل، ومس الفرج، والردة، وزوال العقل، وال‍جنابة.",
      "section": "الطهارة"
    },
    {
      "id": 152,
      "q": "ما حكم البول في ال‍م‍اء الراكد؟",
      "a": "لا ي‍جوز.",
      "section": "الطهارة"
    },
    {
      "id": 153,
      "q": "ما حكم الإسراف في ال‍م‍اء؟",
      "a": "لا ي‍جوز؛ فإن ال‍مبذرين إخوان الشياطين.",
      "section": "الطهارة"
    },
    {
      "id": 154,
      "q": "إذا أسلم الكافر فهل يغتسل؟",
      "a": "نعم.",
      "section": "الطهارة"
    },
    {
      "id": 155,
      "q": "ماذا يفعل إذا ل‍م ي‍جد ال‍م‍اء أو كان استعم‍ال ال‍م‍اء يضره؟",
      "a": "يتيمم بالتراب.",
      "section": "الطهارة"
    },
    {
      "id": 156,
      "q": "اذكر كيفية التيمم؟",
      "a": "يضرب بيديه الأرض ضربة واحدة، ثم ينفخ فيهم‍ا، ويمسح الشم‍ال على اليمين، وظاهر كفيه، ووجهه.",
      "section": "الطهارة"
    },
    {
      "id": 157,
      "q": "ما حكم ال‍مسح على ال‍خفين؟",
      "a": "سنة إذا أدخلهم‍ا طاهرتين.",
      "section": "الطهارة"
    },
    {
      "id": 158,
      "q": "كم يمسح ال‍مسافر وال‍مقيم؟",
      "a": "ال‍مسافر ثلاثة أيام بلياليهن، وال‍مقيم يوما وليلة.",
      "section": "الطهارة"
    },
    {
      "id": 159,
      "q": "من هم الذين ينكرون ال‍مسح على ال‍خفين؟",
      "a": "الشيعة.",
      "section": "الطهارة"
    },
    {
      "id": 160,
      "q": "ما حكم الصلاة في النعال الطاهرة؟",
      "a": "مستحبة.",
      "section": "الطهارة"
    },
    {
      "id": 161,
      "q": "كيف ينادى للصلاة؟",
      "a": "بالأذان.",
      "section": "الأذان"
    },
    {
      "id": 162,
      "q": "اذكر صيغة الأذان؟",
      "a": "الله أكبر[1] الله أكبر[2]، الله أكبر[3] الله أكبر[4]، أشهد أن لا إله إلا الله [5] أشهد أن لا إله إلا الله[6]، أشهد أن م‍حمدا رسول الله[7] أشهد أن م‍حمدا رسول الله[8]، حي على الصلاة[9] حي على الصلاة[10]، حي على الفلاح[11] حي على الفلاح[12]، الله أكبر[13] الله أكبر[14]، لا إله إلا الله[15].",
      "section": "الأذان"
    },
    {
      "id": 163,
      "q": "ماذا نزيد في الأذان الأول لصلاة الصبح؟",
      "a": "الصلاة خير من النوم [مرتين] بعد: (حي على الفلاح).",
      "section": "الأذان"
    },
    {
      "id": 164,
      "q": "ماذا يقول ال‍مؤذن إذا نزل ال‍مطر وشق على الناس ال‍خروج للصلاة؟",
      "a": "صلوا في رحالكم، أو صلوا في بيوتكم.",
      "section": "الأذان"
    },
    {
      "id": 165,
      "q": "ما حكم قول (حي على خير العمل) في الأذان؟",
      "a": "بدعة من بدع الشيعة.",
      "section": "الأذان"
    },
    {
      "id": 166,
      "q": "ما هو عمود الإسلام؟",
      "a": "الصلاة.",
      "section": "الصلاة والمساجد"
    },
    {
      "id": 167,
      "q": "ما حكم ترك الصلاة؟",
      "a": "ترك الصلاة كفر.",
      "section": "الصلاة والمساجد"
    },
    {
      "id": 168,
      "q": "متى فرض الله على نبيه الصلاة؟",
      "a": "ليلة الإسراء.",
      "section": "الصلاة والمساجد"
    },
    {
      "id": 169,
      "q": "كم عدد الصلوات ال‍مفروضة؟",
      "a": "خمس صلوات في كل يوم وليلة.",
      "section": "الصلاة والمساجد"
    },
    {
      "id": 170,
      "q": "اذكر عدد ركعات كل صلاة؟",
      "a": "الفجر: ركعتان، الظهر: أربع ركعات، العصر: أربع ركعات، ال‍مغرب: ثلاث ركعات، العشاء: أربع ركعات.",
      "section": "الصلاة والمساجد"
    },
    {
      "id": 171,
      "q": "ما حكم من صلى الصلاة في غير وقتها؟",
      "a": "صلاته باطلة.",
      "section": "الصلاة والمساجد"
    },
    {
      "id": 172,
      "q": "ما الدليل على أن كل صلاة تصلى في وقتها؟",
      "a": "قال تعالى: (إن الصلاة كانت على المؤمنين كتابا موقوتا) [سورة النساء:103].",
      "section": "الصلاة والمساجد"
    },
    {
      "id": 173,
      "q": "ما هي الصلاة الوسطى؟",
      "a": "صلاة العصر.",
      "section": "الصلاة والمساجد"
    },
    {
      "id": 174,
      "q": "ماذا يتخذ ال‍مصلي أمامه إذا أراد الصلاة؟",
      "a": "يتخذ له سترة يصلي إليها.",
      "section": "الصلاة والمساجد"
    },
    {
      "id": 175,
      "q": "ماذا يفعل ال‍مصلي إذا أراد أحد أن يمر بينه وبين السترة؟",
      "a": "يرده.",
      "section": "الصلاة والمساجد"
    },
    {
      "id": 176,
      "q": "ما هي الأشياء التي تقطع الصلاة؟",
      "a": "ال‍مرأة البالغ، ال‍حم‍ار، الكلب الأسود.",
      "section": "الصلاة والمساجد"
    },
    {
      "id": 177,
      "q": "إلى أين يتوجه ال‍مصلي؟",
      "a": "إلى الكعبة، قال تعالى: (ومن حيث خرجت فول وجهك شطر المسجد الحرام وحيث ما كنتم فولوا وجوهكم شطره) [سورة البقرة:150].",
      "section": "الصلاة والمساجد"
    },
    {
      "id": 178,
      "q": "كيف يصلي ال‍مريض؟",
      "a": "قائم‍ا، فإن ل‍م يستطع فقاعدا، فإن ل‍م يستطع فعلى جنب.",
      "section": "الصلاة والمساجد"
    },
    {
      "id": 179,
      "q": "ماذا يفعل ال‍مصلي حين يكبر؟",
      "a": "يرفع يديه إلى حذو منكبيه.",
      "section": "الصلاة والمساجد"
    },
    {
      "id": 180,
      "q": "أين يضع ال‍مصلي يديه؟",
      "a": "يضع يده اليمنى على يده اليسرى، على صدره أو ت‍حت صدره، والأمر واسع.",
      "section": "الصلاة والمساجد"
    },
    {
      "id": 181,
      "q": "ماذا يقول بعد تكبيرة الإحرام؟",
      "a": "يقرأ دعاء الاستفتاح.",
      "section": "الصلاة والمساجد"
    },
    {
      "id": 182,
      "q": "اذكر دعاء الاستفتاح؟",
      "a": "اللهم باعد بيني وبين خطاياي، كم‍ا باعدت بين ال‍مشرق وال‍مغرب، اللهم نقني من ال‍خطايا كم‍ا ينقى الثوب الأبيض من الدنس، اللهم اغسل خطاياي بال‍م‍اء والثلج والبرد.",
      "section": "الصلاة والمساجد"
    },
    {
      "id": 183,
      "q": "ماذا تقرأ بعد الاستفتاح؟",
      "a": "الاستعاذة: (أعوذ بالله من الشيطان الرجيم).",
      "section": "الصلاة والمساجد"
    },
    {
      "id": 184,
      "q": "ماذا تقرأ بعد الاستعاذة؟",
      "a": "البسملة: (بسم الله الرحمن الرحيم).",
      "section": "الصلاة والمساجد"
    },
    {
      "id": 185,
      "q": "هل تكون الاستعاذة والبسملة سرا أم جهرا؟",
      "a": "سرا.",
      "section": "الصلاة والمساجد"
    },
    {
      "id": 186,
      "q": "ماذا تقرأ بعد البسملة؟",
      "a": "الفات‍حة، وما تيسر من القرآن.",
      "section": "الصلاة والمساجد"
    },
    {
      "id": 187,
      "q": "ماذا تقول بعد الفات‍حة؟",
      "a": "آمين.",
      "section": "الصلاة والمساجد"
    },
    {
      "id": 188,
      "q": "ما هو الأجر ال‍مترتب على قول (آمين) بعد الفات‍حة في الصلاة؟",
      "a": "إذا وافق تأمينه تأمين ال‍ملائكة غفر له ما تقدم من ذنبه.",
      "section": "الصلاة والمساجد"
    },
    {
      "id": 189,
      "q": "ما حكم من ل‍م يقرأ بفات‍حة الكتاب؟",
      "a": "صلاته باطلة.",
      "section": "الصلاة والمساجد"
    },
    {
      "id": 190,
      "q": "ما حكم رفع البصر إلى السماء في الصلاة؟",
      "a": "لا ي‍جوز.",
      "section": "الصلاة والمساجد"
    },
    {
      "id": 191,
      "q": "اذكر بعض ما يقال في الركوع، والرفع من الركوع؟",
      "a": "في الركوع: (سبحان ربي العظيم) ثلاثا. (سبوح، قدوس، رب ال‍ملائكة والروح). (سبحانك اللهم وبحمدك اللهم اغفر لي). وفي الرفع من الركوع: (سمع الله ل‍من حمده، ربنا ولك ال‍حمد).",
      "section": "الصلاة والمساجد"
    },
    {
      "id": 192,
      "q": "ما هي أعضاء السجود؟",
      "a": "سبعة: (1-2) اليدان، (3-4) والركبتان، (5) وال‍جبهة مع الأنف، (6-7) وأطراف القدمين.",
      "section": "الصلاة والمساجد"
    },
    {
      "id": 193,
      "q": "اذكر بعض ما يقال في السجود؟",
      "a": "(سبحان ربي الأعلى) ثلاثا، (اللهم اغفر لي ذنبي كله، دقه وجله، وأوله وآخره، وعلانيته وسره)، (اللهم يا مقلب القلوب ثبت قلبي على دينك).",
      "section": "الصلاة والمساجد"
    },
    {
      "id": 194,
      "q": "ماذا نقول بين السجدتين؟",
      "a": "نقول: (رب اغفر لي، رب اغفر لي).",
      "section": "الصلاة والمساجد"
    },
    {
      "id": 195,
      "q": "اذكر التشهد؟",
      "a": "التحيات لله والصلوات والطيبات، السلام عليك أيها النبي ورحمة الله وبركاته، السلام علينا وعلى عباد الله الصال‍حين، أشهد أن لا إله إلا الله وأشهد أن م‍حمدا عبده ورسوله.",
      "section": "الصلاة والمساجد"
    },
    {
      "id": 196,
      "q": "اذكر الصلاة الإبراهيمية؟",
      "a": "اللهم صل على م‍حمد وعلى آل م‍حمد، كما صليت على إبراهيم وعلى آل إبراهيم، إنك حميد م‍جيد، اللهم بارك على م‍حمد وعلى آل م‍حمد، كما باركت على إبراهيم وعلى آل إبراهيم، إنك حميد م‍جيد.",
      "section": "الصلاة والمساجد"
    },
    {
      "id": 197,
      "q": "ماذا يقول بعد الصلاة الإبراهيمية؟",
      "a": "يستعيذ بالله من أربع: من عذاب القبر، ومن عذاب جهنم، ومن فتنة ال‍محيا وال‍مم‍ات، ومن فتنة ال‍مسيح الدجال.",
      "section": "الصلاة والمساجد"
    },
    {
      "id": 198,
      "q": "ما حكم الذي يضحك في صلاته؟",
      "a": "صلاته باطلة.",
      "section": "الصلاة والمساجد"
    },
    {
      "id": 199,
      "q": "كم الصلوات الرواتب؟",
      "a": "ركعتان قبل صلاة الصبح، أربع قبل الظهر وركعتان بعدها، ركعتان بعد ال‍مغرب، ركعتان بعد العشاء.",
      "section": "الصلاة والمساجد"
    },
    {
      "id": 200,
      "q": "ما هو الأجر ال‍مترتب على من حافظ على هذه الرواتب كل يوم؟",
      "a": "يبنى له بيت في ال‍جنة.",
      "section": "الصلاة والمساجد"
    },
    {
      "id": 201,
      "q": "أي‍هم‍ا أفضل في النوافل: أن تصلى في ال‍مسجد أم في البيت؟",
      "a": "في البيت.",
      "section": "الصلاة والمساجد"
    },
    {
      "id": 202,
      "q": "أين تصلى الفرائض؟",
      "a": "تصلى في ال‍مسجد مع ال‍جم‍اعة.",
      "section": "الصلاة والمساجد"
    },
    {
      "id": 203,
      "q": "هل يسرع في ال‍مشي إلى الصلاة؟",
      "a": "لا، بل يمشي بسكينة ووقار.",
      "section": "الصلاة والمساجد"
    },
    {
      "id": 204,
      "q": "ما هما الركعتان اللتان هما خير من الدنيا وما فيها؟",
      "a": "سنة الصبح.",
      "section": "الصلاة والمساجد"
    },
    {
      "id": 205,
      "q": "كم صلاة الضحى؟",
      "a": "أقلها ركعتان، وله أن يزيد ما شاء الله.",
      "section": "الصلاة والمساجد"
    },
    {
      "id": 206,
      "q": "بكم تفضل صلاة ال‍جم‍اعة على صلاة الفرد؟",
      "a": "بسبع وعشرين درجة.",
      "section": "الصلاة والمساجد"
    },
    {
      "id": 207,
      "q": "ما هي أفضل صفوف الرجال؟",
      "a": "أول‍ها.",
      "section": "الصلاة والمساجد"
    },
    {
      "id": 208,
      "q": "ما هي أفضل صفوف النساء؟",
      "a": "آخرها.",
      "section": "الصلاة والمساجد"
    },
    {
      "id": 209,
      "q": "ما أجر من وصل صفا؟",
      "a": "من وصل صفا وصله الله.",
      "section": "الصلاة والمساجد"
    },
    {
      "id": 210,
      "q": "من الذي يؤم الناس؟",
      "a": "أقرؤهم لكتاب الله.",
      "section": "الصلاة والمساجد"
    },
    {
      "id": 211,
      "q": "هل ي‍جوز أن تؤم ال‍مرأة الرجال؟",
      "a": "لا ي‍جوز ذلك.",
      "section": "الصلاة والمساجد"
    },
    {
      "id": 212,
      "q": "إذا دخل ال‍مسجد وأراد أن ي‍جلس، فم‍اذا يفعل؟",
      "a": "يصلي ركعتين ت‍حية ال‍مسجد.",
      "section": "الصلاة والمساجد"
    },
    {
      "id": 213,
      "q": "أين يصلي من أكل ثوما أو بصلا أو كراثا؟",
      "a": "يصلي في بيته، ولا يقرب ال‍مسجد.",
      "section": "الصلاة والمساجد"
    },
    {
      "id": 214,
      "q": "هل ي‍جوز أخذ كتاب أو مصحف من ال‍مسجد؟",
      "a": "لا ي‍جوز؛ لأنها وقف للمسجد.",
      "section": "الصلاة والمساجد"
    },
    {
      "id": 215,
      "q": "هل ي‍جوز البيع والشراء في ال‍مسجد؟",
      "a": "لا ي‍جوز؛ وإنم‍ا بنيت ال‍مساجد لذكر الله",
      "section": "الصلاة والمساجد"
    },
    {
      "id": 216,
      "q": "هل ي‍جوز رفع الأصوات في ال‍مساجد في غير الذكر؟",
      "a": "لا ي‍جوز.",
      "section": "الصلاة والمساجد"
    },
    {
      "id": 217,
      "q": "هل ت‍جوز الصلاة في ال‍مساجد التي فيها قبور؟",
      "a": "لا ت‍جوز.",
      "section": "الصلاة والمساجد"
    },
    {
      "id": 218,
      "q": "هل ي‍جوز البيع والشراء يوم ال‍جمعة بعد الأذان؟",
      "a": "لا ي‍جوز.",
      "section": "الصلاة والمساجد"
    },
    {
      "id": 219,
      "q": "هل ي‍جوز رد السلام أثناء خطبة ال‍جمعة؟",
      "a": "لا ي‍جوز، ومن تكلم فقد لغا، ومن لغا فلا جمعة له.",
      "section": "الصلاة والمساجد"
    },
    {
      "id": 220,
      "q": "ما حكم من تكلم والإمام ي‍خطب يوم ال‍جمعة؟",
      "a": "لا جمعة له.",
      "section": "الصلاة والمساجد"
    },
    {
      "id": 221,
      "q": "هل في صلاة العيد أذان وإقامة؟",
      "a": "لا.",
      "section": "الصلاة والمساجد"
    },
    {
      "id": 222,
      "q": "ما هي أحسن الثياب؟",
      "a": "الثياب البيض.",
      "section": "الجنائز"
    },
    {
      "id": 223,
      "q": "ما هو الأجر ال‍مترتب على الصلاة على ال‍جنازة؟",
      "a": "من صلى عليها فله قيراط.",
      "section": "الجنائز"
    },
    {
      "id": 224,
      "q": "ما هو الأجر ال‍مترتب على اتباع ال‍جنازة؟",
      "a": "من تبعها فله قيراط.",
      "section": "الجنائز"
    },
    {
      "id": 225,
      "q": "كم مقدار هذا القيراط؟",
      "a": "كل قيراط مثل جبل أحد.",
      "section": "الجنائز"
    },
    {
      "id": 226,
      "q": "هل ي‍جوز ال‍جلوس على القبر، أو وطؤه، أو ت‍خطي القبور بالنعال؟",
      "a": "لا ي‍جوز.",
      "section": "الجنائز"
    },
    {
      "id": 227,
      "q": "ما حكم صيام رمضان؟",
      "a": "ركن من أركان الإسلام.",
      "section": "الصيام والحج"
    },
    {
      "id": 228,
      "q": "ما اسم الباب من أبواب ال‍جنة الذي لا يدخل منه إلا الصائمون؟",
      "a": "باب الريان.",
      "section": "الصيام والحج"
    },
    {
      "id": 229,
      "q": "ما أعظم ليلة في السنة؟",
      "a": "ليلة القدر في رمضان.",
      "section": "الصيام والحج"
    },
    {
      "id": 230,
      "q": "ما فضل ليلة القدر؟ وقيامها؟",
      "a": "هي خير من ألف شهر. ومن قامها إيم‍انا واحتسابا غفر له ما تقدم من ذنبه.",
      "section": "الصيام والحج"
    },
    {
      "id": 231,
      "q": "كم ي‍جب ال‍حج في العمر؟",
      "a": "مرة واحدة.",
      "section": "الصيام والحج"
    },
    {
      "id": 232,
      "q": "هل ي‍جوز أكل ال‍جراد؟",
      "a": "نعم؛ فقد أكله الصحابة في بعض الغزوات.",
      "section": "أحكام متفرقة"
    },
    {
      "id": 233,
      "q": "هل ي‍جوز أكل ذبيحة الذي لا يسمى الله؟",
      "a": "لا، لقوله تعالى: (ولا تأكلوا مما لم يذكر اسم الله عليه وإنه لفسق) [سورة الأنعام:121].",
      "section": "أحكام متفرقة"
    },
    {
      "id": 234,
      "q": "ما حكم لبس ال‍حرير والذهب؟",
      "a": "حلال للإناث، وحرام على الذكور.",
      "section": "أحكام متفرقة"
    },
    {
      "id": 235,
      "q": "ما هي أم ال‍خبائث؟",
      "a": "هي ال‍خمر.",
      "section": "أحكام متفرقة"
    },
    {
      "id": 236,
      "q": "إلى أين يكون إزار ال‍مسلم وثوبه؟",
      "a": "الأفضل إلى نصف الساق، وي‍جوز إلى فوق الكعب.",
      "section": "أحكام متفرقة"
    },
    {
      "id": 237,
      "q": "ما حكم من زاد على الكعب؟",
      "a": "حرام؛ ما أسفل الكعبين ففي النار.",
      "section": "أحكام متفرقة"
    },
    {
      "id": 238,
      "q": "هل ي‍جوز لبس البنطال؟",
      "a": "لا ي‍جوز؛ لأنه تشبه بالكفار.",
      "section": "أحكام متفرقة"
    },
    {
      "id": 239,
      "q": "هل ي‍جوز للرجل أن يلبس لبس النساء أو العكس؟",
      "a": "لا ي‍جوز ذلك.",
      "section": "أحكام متفرقة"
    },
    {
      "id": 240,
      "q": "ما حكم حلق اللحية، أو التقصير منها؟",
      "a": "حرام.",
      "section": "أحكام متفرقة"
    },
    {
      "id": 241,
      "q": "ل‍م‍اذا ن‍هى رسول الله ‘ عن ال‍خذف؟",
      "a": "لأنه لا يصيد الصيد، وإنم‍ا يفقأ العين ويكسر السن.",
      "section": "أحكام متفرقة"
    },
    {
      "id": 242,
      "q": "هل ي‍جوز أن نقتل النمل، أو غيرها من ال‍حشرات حرقا بالنار؟",
      "a": "لا ي‍جوز ذلك.",
      "section": "أحكام متفرقة"
    },
    {
      "id": 243,
      "q": "هل ي‍جوز إضاعة ال‍م‍ال؟",
      "a": "لا ي‍جوز.",
      "section": "أحكام متفرقة"
    },
    {
      "id": 244,
      "q": "هل ي‍جوز بيع الكلب؟",
      "a": "لا ي‍جوز، فثمنه حرام.",
      "section": "أحكام متفرقة"
    },
    {
      "id": 245,
      "q": "ما حكم اقتناء الكلاب؟",
      "a": "لا ي‍جوز، إلا إذا كان كلب صيد أو ماشية أو زرع.",
      "section": "أحكام متفرقة"
    },
    {
      "id": 246,
      "q": "ما حكم التشبه باليهود، والنصارى، وال‍مشركين؟ وما الدليل؟",
      "a": "حرام. قال رسول الله ‘: «من تشبه بقوم فهو منهم». رواه أبوداود.",
      "section": "أحكام متفرقة"
    },
    {
      "id": 247,
      "q": "ل‍م‍اذا حرم الأكل والشرب بالشم‍ال؟",
      "a": "لأن الشيطان يأكل ويشرب بشم‍اله.",
      "section": "أحكام متفرقة"
    },
    {
      "id": 248,
      "q": "ما حكم الشرب قائم‍ا؟",
      "a": "مكروه.",
      "section": "أحكام متفرقة"
    },
    {
      "id": 249,
      "q": "ما حكم استم‍اع الأغاني؟",
      "a": "م‍حرم.",
      "section": "أحكام متفرقة"
    },
    {
      "id": 250,
      "q": "هل ي‍جوز النظر إلى الصور ال‍خليعة؟",
      "a": "لا ي‍جوز.",
      "section": "أحكام متفرقة"
    },
    {
      "id": 251,
      "q": "ما هي أصح الكتب ال‍مصنفة؟",
      "a": "صحيح البخاري، وصحيح مسلم.",
      "section": "مؤلفات وعلماء"
    },
    {
      "id": 252,
      "q": "اذكر أربعة من أبرز علم‍اء اليمن ال‍متقدمين؟",
      "a": "عبدالرزاق بن همام الصنعاني، م‍حمد بن إبراهيم الوزير، م‍حمد بن إسم‍اعيل الأمير، م‍حمد بن علي الشوكاني رحمهم الله.",
      "section": "مؤلفات وعلماء"
    },
    {
      "id": 253,
      "q": "اذكر أربعة من م‍جددي هذا العصر؟",
      "a": "ابن باز، والألباني، والعثيمين، والوادعي رحمهم الله.",
      "section": "مؤلفات وعلماء"
    },
    {
      "id": 254,
      "q": "من هم ورثة الأنبياء؟",
      "a": "هم العلم‍اء.",
      "section": "مؤلفات وعلماء"
    },
    {
      "id": 255,
      "q": "ما حكم طلب العلم؟",
      "a": "فريضة على كل مسلم.",
      "section": "مؤلفات وعلماء"
    },
    {
      "id": 256,
      "q": "ماذا يقول عند الاستيقاظ من النوم؟",
      "a": "ال‍حمد لله الذي أحيانا بعد ما أماتنا، وإليه النشور.",
      "section": "الأذكار والآداب والفضائل"
    },
    {
      "id": 257,
      "q": "ماذا يقول عند بداية الوضوء؟",
      "a": "بسم الله.",
      "section": "الأذكار والآداب والفضائل"
    },
    {
      "id": 258,
      "q": "ماذا يقول عند الفراغ من الوضوء؟",
      "a": "أشهد أن لا إله إلا الله وحده لا شريك له، وأشهد أن م‍حمدا عبده ورسوله.",
      "section": "الأذكار والآداب والفضائل"
    },
    {
      "id": 259,
      "q": "ماذا يقول عند دخول ال‍حم‍ام؟",
      "a": "اللهم إني أعوذ بك من ال‍خبث وال‍خبائث.",
      "section": "الأذكار والآداب والفضائل"
    },
    {
      "id": 260,
      "q": "أي الرجلين يقدم عند دخول ال‍حم‍ام؟",
      "a": "الرجل اليسرى.",
      "section": "الأذكار والآداب والفضائل"
    },
    {
      "id": 261,
      "q": "هل ي‍جوز أن يذكر الله أثناء قضاء ال‍حاجة؟",
      "a": "لا ي‍جوز له ذلك.",
      "section": "الأذكار والآداب والفضائل"
    },
    {
      "id": 262,
      "q": "ماذا يقدم عند ال‍خروج من ال‍حم‍ام؟",
      "a": "الرجل اليمنى.",
      "section": "الأذكار والآداب والفضائل"
    },
    {
      "id": 263,
      "q": "ماذا يقول عند ال‍خروج؟",
      "a": "غفرانك.",
      "section": "الأذكار والآداب والفضائل"
    },
    {
      "id": 264,
      "q": "ماذا يقول إذا سمع ال‍مؤذن؟",
      "a": "يقول مثل م‍ا يقول، إلا في (حي على الصلاة حي على الفلاح) فيقول: لا حول ولا قوة إلا بالله.",
      "section": "الأذكار والآداب والفضائل"
    },
    {
      "id": 265,
      "q": "ماذا يقول بعد الأذان؟",
      "a": "يصلي على النبي ‘، ثم يقول: اللهم رب هذه الدعوة التامة، والصلاة القائمة، آت م‍حمدا الوسيلة والفضيلة، وابعثه مقاما م‍حمودا الذي وعدته.",
      "section": "الأذكار والآداب والفضائل"
    },
    {
      "id": 266,
      "q": "ماذا يقول إذا سمع صياح الديكة؟",
      "a": "اللهم إني أسألك من فضلك.",
      "section": "الأذكار والآداب والفضائل"
    },
    {
      "id": 267,
      "q": "ماذا يقول عند خروجه من البيت؟",
      "a": "يقول: بسم الله توكلت على الله اللهم أعوذ بك أن أضل، أو أضل، أو أزل، أو أزل، أو أظلم، أو أظلم، أو أجهل، أو يجهل علي.",
      "section": "الأذكار والآداب والفضائل"
    },
    {
      "id": 268,
      "q": "ماذا يقول عند دخول ال‍مسجد وعند ال‍خروج منه؟",
      "a": "عند الدخول يقول: اللهم افتح لي أبواب رحمتك. أعوذ بالله العظيم، وبوجهه الكريم، وسلطانه القديم، من الشيطان الرجيم. وعند ال‍خروج: اللهم إني أسألك من فضلك.",
      "section": "الأذكار والآداب والفضائل"
    },
    {
      "id": 269,
      "q": "أي الرجلين يقدم عند الدخول إلى ال‍مسجد؟",
      "a": "الرجل اليمنى.",
      "section": "الأذكار والآداب والفضائل"
    },
    {
      "id": 270,
      "q": "ما هو دعاء الركوب؟",
      "a": "هو (سبحان الذي سخر لنا هذا وما كنا له مقرنين وإنا إلى ربنا لمنقلبون) [سورة الزخرف:13-14].",
      "section": "الأذكار والآداب والفضائل"
    },
    {
      "id": 271,
      "q": "ماذا يقول في أول الطعام وفي آخره؟",
      "a": "يقول في أوله: بسم الله. وفي آخره: ال‍حمد لله.",
      "section": "الأذكار والآداب والفضائل"
    },
    {
      "id": 272,
      "q": "ماذا يفعل ال‍مسلم إذا تثاءب؟",
      "a": "يكظم ما استطاع، ويضع يده على فيه.",
      "section": "الأذكار والآداب والفضائل"
    },
    {
      "id": 273,
      "q": "ماذا نقول عند نزول ال‍مطر؟",
      "a": "اللهم صيبا نافعا.",
      "section": "الأذكار والآداب والفضائل"
    },
    {
      "id": 274,
      "q": "ماذا يقول من غضب؟",
      "a": "أعوذ بالله من الشيطان الرجيم.",
      "section": "الأذكار والآداب والفضائل"
    },
    {
      "id": 275,
      "q": "هل تسلم على من تعرفه فقط؟",
      "a": "لا، بل على من عرفت، ومن ل‍م تعرف.",
      "section": "الأذكار والآداب والفضائل"
    },
    {
      "id": 276,
      "q": "هل تسلم على الصبيان الصغار؟",
      "a": "نعم، فقد كان النبي ‘ يسلم عليهم.",
      "section": "الأذكار والآداب والفضائل"
    },
    {
      "id": 277,
      "q": "ماذا تقول إذا زرت مريضا؟",
      "a": "لا بأس طهور إن شاء الله.",
      "section": "الأذكار والآداب والفضائل"
    },
    {
      "id": 278,
      "q": "ما فضل (لا حول ولا قوة إلا بالله)؟",
      "a": "كنز من كنوز ال‍جنة.",
      "section": "الأذكار والآداب والفضائل"
    },
    {
      "id": 279,
      "q": "ما جزاء من صام رمضان،أو قامه إيم‍انا واحتسابا؟",
      "a": "غفر له ما تقدم من ذنبه.",
      "section": "الأذكار والآداب والفضائل"
    },
    {
      "id": 280,
      "q": "بكم تكون الصلاة في ال‍مسجد ال‍حرام؟",
      "a": "بم‍ائة ألف صلاة.",
      "section": "الأذكار والآداب والفضائل"
    },
    {
      "id": 281,
      "q": "بكم تكون الصلاة في ال‍مسجد النبوي؟",
      "a": "بألف صلاة.",
      "section": "الأذكار والآداب والفضائل"
    },
    {
      "id": 282,
      "q": "ما هو أجر من بنى لله مسجدا؟",
      "a": "بنى الله له بيتا في ال‍جنة.",
      "section": "الأذكار والآداب والفضائل"
    },
    {
      "id": 283,
      "q": "ما أجر من قرأ آية الكرسي بعد الفريضة؟",
      "a": "لا يمنعه من دخول ال‍جنة إلا ال‍موت.",
      "section": "الأذكار والآداب والفضائل"
    },
    {
      "id": 284,
      "q": "ما فضل قراءة آية الكرسي عند النوم؟",
      "a": "لا يقربه شيطان، ولا يزال عليه من الله حافظ حتى يصبح.",
      "section": "الأذكار والآداب والفضائل"
    },
    {
      "id": 285,
      "q": "ماذا تفعل إذا رأيت شوكا أو حجرا في الطريق؟",
      "a": "نبعده عن الطريق.",
      "section": "الأذكار والآداب والفضائل"
    },
    {
      "id": 286,
      "q": "هل ال‍مؤمن يكون كريم‍ا أم بخيلا؟",
      "a": "يكون كريم‍ا، والبخل داء عظيم.",
      "section": "الأذكار والآداب والفضائل"
    },
    {
      "id": 287,
      "q": "ما هو أجر من زار أخاه ال‍مسلم؟",
      "a": "يقال له: طبت وطاب م‍مشاك وتبوأت من ال‍جنة منزلا.",
      "section": "الأذكار والآداب والفضائل"
    },
    {
      "id": 288,
      "q": "إذا كان ال‍مجلس فيه كبار وصغار، فمن يبدأ بالكلام؟",
      "a": "الكبير.",
      "section": "الأذكار والآداب والفضائل"
    },
    {
      "id": 289,
      "q": "هل ي‍جوز أن تأخذ أولاد الطيور من عشها؟",
      "a": "لا ي‍جوز ذلك.",
      "section": "الأذكار والآداب والفضائل"
    },
    {
      "id": 290,
      "q": "ماذا تفعل إذا رأيت كلبا أو حيوانا عطشانا؟",
      "a": "أسقيه من ال‍م‍اء.",
      "section": "الأذكار والآداب والفضائل"
    },
    {
      "id": 291,
      "q": "ما خطورة الكذب؟",
      "a": "الكذب ي‍هدي إلى الفجور، والفجور ي‍هدي إلى النار.",
      "section": "الأذكار والآداب والفضائل"
    },
    {
      "id": 292,
      "q": "ما أجر الصدق؟",
      "a": "الصدق ي‍هدي إلى البر، والبر ي‍هدي إلى ال‍جنة.",
      "section": "الأذكار والآداب والفضائل"
    },
    {
      "id": 293,
      "q": "ماذا تفعل إذا رأيت اثنين يتخاصم‍ان؟",
      "a": "أصلح بينهم‍ا؛ قال الله تعالى: (إنما المؤمنون إخوة ‌فأصلحوا بين أخويكم) [سورة الحجرات:10].",
      "section": "الأذكار والآداب والفضائل"
    },
    {
      "id": 294,
      "q": "ما حكم سب ال‍مسلم؟",
      "a": "سباب ال‍مسلم فسوق، لا ي‍جوز.",
      "section": "الأذكار والآداب والفضائل"
    },
    {
      "id": 295,
      "q": "ل‍م‍اذا أمرنا الله بكف الصبيان مع ال‍مغرب؟",
      "a": "لأن الشياطين تنتشر حينئذ.",
      "section": "الأذكار والآداب والفضائل"
    },
    {
      "id": 296,
      "q": "أين يبيت الشيطان مع الإنسان؟",
      "a": "على خيشومه.",
      "section": "الأذكار والآداب والفضائل"
    },
    {
      "id": 297,
      "q": "هل ت‍خرج من البيت بغير إذن والديك؟",
      "a": "لا يصلح ذلك.",
      "section": "الأذكار والآداب والفضائل"
    },
    {
      "id": 298,
      "q": "ما هي ب‍هيمة الأنعام؟",
      "a": "الإبل، والبقر، والغنم.",
      "section": "معلومات متفرقة"
    },
    {
      "id": 299,
      "q": "متى تقوم الساعة؟",
      "a": "لا يعلم ذلك إلا الله.",
      "section": "معلومات متفرقة"
    },
    {
      "id": 300,
      "q": "بم‍اذا ثبت الله الأرض؟",
      "a": "بال‍جبال.",
      "section": "معلومات متفرقة"
    },
    {
      "id": 301,
      "q": "ما هي أم القرى؟",
      "a": "هي: مكة.",
      "section": "معلومات متفرقة"
    },
    {
      "id": 302,
      "q": "ما هي طيبة وطابة؟",
      "a": "هي: ال‍مدينة.",
      "section": "معلومات متفرقة"
    },
    {
      "id": 303,
      "q": "ما هي أحب بلدة إلى الله ورسوله صلى الله عليه وسلم؟",
      "a": "مكة.",
      "section": "معلومات متفرقة"
    },
    {
      "id": 304,
      "q": "ما هو البيت العتيق؟",
      "a": "هو ال‍مسجد ال‍حرام.",
      "section": "معلومات متفرقة"
    },
    {
      "id": 305,
      "q": "قال النبي: «آية ال‍منافق ثلاث» اذكرها؟",
      "a": "إذا حدث كذب، وإذا وعد أخلف، وإذا اؤت‍من خان.",
      "section": "معلومات متفرقة"
    },
    {
      "id": 306,
      "q": "ما أحب الأسم‍اء إلى الله؟",
      "a": "عبدالله، وعبدالرحمن.",
      "section": "معلومات متفرقة"
    },
    {
      "id": 307,
      "q": "ما اسم ال‍حيوان الذي كان ينفخ النار على إبراهيم عليه السلام؟",
      "a": "الوزغة.",
      "section": "معلومات متفرقة"
    },
    {
      "id": 308,
      "q": "ما أجر من قتل وزغة؟",
      "a": "من قتلها في الضربة الأولى فله مائة حسنة.",
      "section": "معلومات متفرقة"
    }
  ],
  "about": {
    "title": "منتقى كنز الأطفال",
    "body": [
      "هذا التطبيق يقدّم كتابًا تعليميًا للأطفال والمبتدئين في عقيدة أهل السنة والجماعة، بعنوان <strong>«منتقى كنز الأطفال»</strong>، من إعداد <strong>الأستاذ فيصل بن مسفر الوادعي</strong>، مع مساعدة في إعداد النص من قِبَل: عبد الرحمن بن ميهوب القداري.",
      "يضمّ التطبيق <strong>٣٠٨ سؤالًا وجوابًا</strong> موزّعة على <strong>١٦ بابًا</strong>، مع مقطع صوتي لكل سؤال. يمكن تصفّح الأسئلة بابًا بابًا، أو البحث بالكلمة في ثوانٍ، وحفظ الأسئلة المفضّلة للرجوع إليها لاحقًا.",
      "يحتوي التطبيق على قسم اختبار بأربعة أنماط مختلفة: الاختيار من متعدد، وترتيب الجواب، وإكمال الكلمة الناقصة، والتعرّف على الجواب بالاستماع. كما يتتبع التطبيق نقاط الضعف تلقائيًا ويقترح مراجعتها.",
      "التطبيق <strong>يعمل بدون إنترنت</strong> بعد أول زيارة — يمكن تثبيته على شاشة الهاتف كتطبيق عادي من خلال زر «إضافة إلى الشاشة الرئيسية»، ويعمل بشكل كامل حتى في غياب الاتصال بالشبكة.",
      "مبادرة فردية لنشر هذا الكتاب القيّم بطريقة منظّمة وسهلة، بدون إعلانات أو تتبّع للمستخدمين، ومجانية تمامًا."
    ],
    "contactTitle": "للتواصل",
    "contacts": [
      {
        "label": "البريد الإلكتروني",
        "value": "abderrahmene_mhb@proton.me",
        "href": "mailto:abderrahmene_mhb@proton.me"
      },
      {
        "label": "تلجرام",
        "value": "@arm_al_qaddaaree",
        "href": "https://t.me/arm_al_qaddaaree"
      }
    ]
  }
}